nuclei_counter/__init__.py
nuclei_counter/__version__.py
nuclei_counter/count_nuclei.py
nuclei_counter/counter.py
nuclei_counter-0.1.0.dist-info/LICENSE
nuclei_counter-0.1.0.dist-info/METADATA
nuclei_counter-0.1.0.dist-info/WHEEL
nuclei_counter-0.1.0.dist-info/RECORD
