Metadata-Version: 2.1
Name: nuclei-counter
Version: 0.1.0
Summary: 
Author: Ron Budnar
Author-email: budnarr@gmail.com
Requires-Python: >=3.10,<3.13
Classifier: Programming Language :: Python :: 3
Classifier: Programming Language :: Python :: 3.10
Classifier: Programming Language :: Python :: 3.11
Classifier: Programming Language :: Python :: 3.12
Requires-Dist: matplotlib (>=3.8.0,<4.0.0)
Requires-Dist: opencv-python (>=4.8.1.78,<5.0.0.0)
Requires-Dist: pandas (>=2.1.1,<3.0.0)
Requires-Dist: tqdm (>=4.66.1,<5.0.0)
